omnitils/__init__.py
omnitils/_cli/__init__.py
omnitils/_cli/testing.py
omnitils/api/__init__.py
omnitils/api/gdrive.py
omnitils/api/github.py
omnitils/dicts.py
omnitils/enums.py
omnitils/exceptions.py
omnitils/fetch/__init__.py
omnitils/fetch/_core.py
omnitils/fetch/download.py
omnitils/files/__init__.py
omnitils/files/_core.py
omnitils/files/archive.py
omnitils/files/data.py
omnitils/files/folders.py
omnitils/img/__init__.py
omnitils/img/_core.py
omnitils/logs.py
omnitils/metaclass.py
omnitils/modules.py
omnitils/properties.py
omnitils/py.typed
omnitils/schema.py
omnitils/strings.py
omnitils/test/__init__.py
omnitils/test/bench.py
omnitils-1.4.6.dist-info/LICENSE.md
omnitils-1.4.6.dist-info/METADATA
omnitils-1.4.6.dist-info/WHEEL
omnitils-1.4.6.dist-info/RECORD
