Metadata-Version: 2.1
Name: omnitils
Version: 1.4.6
Summary: Universal reusable Python utils for the modern human.
License: MPL-2.0
Keywords: omnitils,utilities,utils,files,schema,test,benchmark,enums,logs,investigamer
Author: Investigamer
Author-email: hexproofsystems@gmail.com
Requires-Python: >=3.10,<3.13
Classifier: Development Status :: 4 - Beta
Classifier: Intended Audience :: Developers
Classifier: License :: OSI Approved
Classifier: License :: OSI Approved :: Mozilla Public License 2.0 (MPL 2.0)
Classifier: Programming Language :: Python :: 3
Classifier: Programming Language :: Python :: 3.10
Classifier: Programming Language :: Python :: 3.11
Classifier: Programming Language :: Python :: 3.12
Classifier: Topic :: Utilities
Requires-Dist: PyYAML (>=6.0.1,<7.0.0)
Requires-Dist: backoff (>=2.2.1,<3.0.0)
Requires-Dist: click (>=8.1.7,<9.0.0)
Requires-Dist: loguru (>=0.7.2,<0.8.0)
Requires-Dist: pathvalidate (>=3.2.0,<4.0.0)
Requires-Dist: pillow (>=10.4.0,<11.0.0)
Requires-Dist: py7zr (>=0.22.0,<0.23.0)
Requires-Dist: pydantic (>=2.9.2,<3.0.0)
Requires-Dist: python-dateutil (>=2.9.0.post0,<3.0.0)
Requires-Dist: ratelimit (>=2.2.1,<3.0.0)
Requires-Dist: requests (>=2.32.3,<3.0.0)
Requires-Dist: tomli (>=2.0.1,<3.0.0)
Requires-Dist: tomlkit (>=0.13.2,<0.14.0)
Requires-Dist: tqdm (>=4.66.1,<5.0.0)
Requires-Dist: yarl (>=1.9.4,<2.0.0)
Project-URL: Changelog, https://github.com/Investigamer/omnitils/blob/main/CHANGELOG.md
Project-URL: Discord, https://discord.gg/magicproxies
Project-URL: Issues, https://github.com/Investigamer/omnitils/issues
Project-URL: Source, https://github.com/Investigamer/omnitils
Project-URL: Sponsor, https://patreon.com/mpcfill
